{"routes":[{"id":"trans-gps:2","name":"11","color":"green","description":null,"code":"11","sort":150,"display":1},{"id":"trans-gps:3","name":"12","color":"blue","description":null,"code":"12","sort":180,"display":1},{"id":"trans-gps:4","name":"5","color":"orange","description":null,"code":"5z","sort":46,"display":1},{"id":"trans-gps:5","name":"13","color":"brown","description":null,"code":"13z","sort":211,"display":1},{"id":"trans-gps:6","name":"4","color":"magenta","description":null,"code":"4z","sort":35,"display":1},{"id":"trans-gps:7","name":"6","color":"sienna","description":null,"code":"6z","sort":90,"display":1},{"id":"trans-gps:9","name":"27","color":"black","description":null,"code":"27z","sort":40,"display":1},{"id":"trans-gps:10","name":"34","color":"navy","description":null,"code":"34z","sort":63,"display":1},{"id":"trans-gps:11","name":"9","color":"magenta","description":null,"code":"9z","sort":101,"display":1},{"id":"trans-gps:12","name":"20","color":"maroon","description":null,"code":"20z","sort":221,"display":1},{"id":"trans-gps:13","name":"29","color":"black","description":null,"code":"29z","sort":53,"display":1},{"id":"trans-gps:14","name":"9A","color":"magenta","description":null,"code":"9az","sort":121,"display":1},{"id":"trans-gps:15","name":"ET","color":"green","description":null,"code":"et","sort":201,"display":1},{"id":"trans-gps:16","name":"2","color":"green","description":null,"code":"2z","sort":6,"display":1},{"id":"trans-gps:17","name":"23","color":"red","description":null,"code":"23z","sort":34,"display":1},{"id":"trans-gps:18","name":"5A","color":"orange","description":null,"code":"5a","sort":60,"display":1},{"id":"trans-gps:20","name":"A","color":"navy","description":null,"code":"a","sort":151,"display":1},{"id":"trans-gps:21","name":"38","color":"deeppink","description":null,"code":"38z","sort":130,"display":1},{"id":"trans-gps:22","name":"37","color":"olive","description":null,"code":"37z","sort":110,"display":1},{"id":"trans-gps:23","name":"36","color":"teal","description":null,"code":"36z","sort":91,"display":1},{"id":"transport-cv:201","name":" Т №1","color":"red","description":"Держуніверситет - вул. Ковальчука","maxDuration":50,"rteId":1},{"id":"transport-cv:402","name":" Т №2","color":"maroon","description":"Держуніверситет -  завод «Гравітон»","maxDuration":55,"rteId":1},{"id":"transport-cv:261","name":" Т №3","color":"fuchsia","description":"Дріжзавод - завод «Кварц»/Училище № 15","maxDuration":null,"rteId":1},{"id":"transport-cv:401","name":" Т №4 ","color":"blue","description":"Університет - Кемпінг","maxDuration":48,"rteId":1},{"id":"transport-cv:302","name":" Т №5","color":"black","description":"Калинівський ринок - вул. Південно-Кільцева","maxDuration":105,"rteId":1},{"id":"transport-cv:303","name":" Т №6","color":"teal","description":"пл. Соборна -  завод «Кварц»/Училище № 15","maxDuration":61,"rteId":1},{"id":"transport-cv:2042","name":"T №11","color":"#00FF00","description":null,"maxDuration":120,"rteId":1},{"id":"transport-cv:2121","name":"T №8","color":"#000000","description":"вул. Південно-Кільцева  - Держуніверситет","maxDuration":null,"rteId":1},{"id":"transport-cv:1101","name":"А № 1","color":"#00FF00","description":null,"maxDuration":200,"rteId":4},{"id":"transport-cv:361","name":"А № 1 a","color":"maroon","description":null,"maxDuration":90,"rteId":4},{"id":"transport-cv:1921","name":"А № 10","color":"fuchsia","description":null,"maxDuration":50,"rteId":4},{"id":"transport-cv:1821","name":"А № 10 а","color":"red","description":null,"maxDuration":50,"rteId":4},{"id":"transport-cv:1222","name":"А № 10 до Александрі","color":"navy","description":null,"maxDuration":150,"rteId":4},{"id":"transport-cv:502","name":"А № 14","color":"#0000FF","description":null,"maxDuration":50,"rteId":4},{"id":"transport-cv:722","name":"А № 15","color":"#800000","description":null,"maxDuration":60,"rteId":4},{"id":"transport-cv:141","name":"А № 16","color":"red","description":null,"maxDuration":90,"rteId":4},{"id":"transport-cv:1231","name":"А № 17","color":"navy","description":null,"maxDuration":150,"rteId":4},{"id":"transport-cv:341","name":"А № 18","color":"maroon","description":"вул. Садова - вул. Дунайська","maxDuration":null,"rteId":4},{"id":"transport-cv:64","name":"А № 19","color":"maroon","description":"вул. Садова - вул. Литовська","maxDuration":null,"rteId":4},{"id":"transport-cv:823","name":"А № 21","color":"#00BFFF","description":null,"maxDuration":150,"rteId":4},{"id":"transport-cv:841","name":"А № 22","color":"maroon","description":"№ 22","maxDuration":150,"rteId":4},{"id":"transport-cv:825","name":"А № 24","color":"teal","description":null,"maxDuration":90,"rteId":4},{"id":"transport-cv:1922","name":"А № 26-26а","color":"teal","description":null,"maxDuration":60,"rteId":4},{"id":"transport-cv:121","name":"А № 3","color":"red","description":"вул.Садова - вул.Вижницька","maxDuration":null,"rteId":4},{"id":"transport-cv:842","name":"А № 33","color":"blue","description":"№33","maxDuration":50,"rteId":4},{"id":"transport-cv:61","name":"А № 33а","color":"fuchsia","description":"№33А","maxDuration":80,"rteId":4},{"id":"transport-cv:863","name":"А № 36","color":"#FF00FF","description":null,"maxDuration":50,"rteId":4},{"id":"transport-cv:1942","name":"А № 37","color":"#FF0000","description":null,"maxDuration":60,"rteId":4},{"id":"transport-cv:501","name":"А № 38","color":"black","description":null,"maxDuration":60,"rteId":4},{"id":"transport-cv:1501","name":"А № 39","color":"blue","description":"вул. Сагайдачного - вул. Комарова","maxDuration":70,"rteId":4},{"id":"transport-cv:706","name":"А № 41","color":"lightgreen","description":null,"maxDuration":60,"rteId":4},{"id":"transport-cv:824","name":"А № 7","color":"#FF0000","description":null,"maxDuration":90,"rteId":4},{"id":"transport-cv:1924","name":"А № 8","color":"fuchsia","description":null,"maxDuration":50,"rteId":4}],"trackers":[{"id":"trans-gps:77","latitude":48.32469,"longitude":25.93434166666667,"direction":0,"speed":0,"datetime":"2018-12-23 22:38:01","routeId":10,"imei":"355227045051273","name":"A7","stateCode":"used","stateName":"used","routeName":"34","routeColour":"navy","inDepo":true,"busNumber":"0994","perevId":1,"perevName":"Денисівка","remark":"0994 карта Т7","online":true},{"id":"trans-gps:78","latitude":48.325035,"longitude":25.933398333333333,"direction":0,"speed":0,"datetime":"2018-12-23 17:51:27","routeId":10,"imei":"355227045370897","name":"A5","stateCode":"used","stateName":"used","routeName":"34","routeColour":"navy","inDepo":false,"busNumber":"0712","perevId":1,"perevName":"Денисівка","remark":"0712 карта Т5","online":true},{"id":"trans-gps:81","latitude":48.27034666666667,"longitude":25.983561666666667,"direction":0,"speed":0,"datetime":"2018-12-23 22:38:19","routeId":23,"imei":"355227045369436","name":"A2","stateCode":"used","stateName":"used","routeName":"36","routeColour":"teal","inDepo":false,"busNumber":"1126","perevId":7,"perevName":"Віталій / Олег Бойко ","remark":"1126 карта Т2","online":true},{"id":"trans-gps:82","latitude":48.305555,"longitude":25.922204999999998,"direction":292.65,"speed":16.4,"datetime":"2018-12-23 22:41:42","routeId":7,"imei":"355227045371655","name":"Am1","stateCode":"used","stateName":"used","routeName":"6","routeColour":"sienna","inDepo":false,"busNumber":"1121","perevId":1,"perevName":"Денисівка","remark":"1121 карта №17","online":true},{"id":"trans-gps:84","latitude":48.251243333333335,"longitude":25.948808333333332,"direction":273.4,"speed":26.4,"datetime":"2018-12-23 22:41:43","routeId":2,"imei":"355227045369873","name":"A10","stateCode":"used","stateName":"used","routeName":"11","routeColour":"green","inDepo":false,"busNumber":"7237","perevId":2,"perevName":"Тарас","remark":"7237 карта Т10","online":true},{"id":"trans-gps:86","latitude":48.324805,"longitude":25.933921666666667,"direction":55.71,"speed":2.5,"datetime":"2018-12-23 22:41:36","routeId":4,"imei":"355227045371341","name":"Am13","stateCode":"used","stateName":"used","routeName":"5","routeColour":"orange","inDepo":true,"busNumber":"0896","perevId":1,"perevName":"Денисівка","remark":"0896 карта №32","online":true},{"id":"trans-gps:89","latitude":48.272038888888886,"longitude":25.928446666666666,"direction":194,"speed":20,"datetime":"2018-12-23 22:41:34","routeId":2,"imei":"0865205032256496","name":"A25","stateCode":"used","stateName":"used","routeName":"11","routeColour":"green","inDepo":false,"busNumber":"0081","perevId":2,"perevName":"Тарас","remark":"0081 карта №7","online":true},{"id":"trans-gps:90","latitude":48.32412333333333,"longitude":25.933796666666666,"direction":0,"speed":0,"datetime":"2018-12-23 22:40:59","routeId":5,"imei":"355227044854636","name":"A16","stateCode":"used","stateName":"used","routeName":"13","routeColour":"brown","inDepo":true,"busNumber":"1066","perevId":1,"perevName":"Денисівка","remark":"1066 карта №27","online":true},{"id":"trans-gps:91","latitude":48.284418333333335,"longitude":25.937818333333333,"direction":336.89,"speed":19.5,"datetime":"2018-12-23 22:41:36","routeId":9,"imei":"355227044854818","name":"A17","stateCode":"used","stateName":"used","routeName":"27","routeColour":"black","inDepo":false,"busNumber":"0106","perevId":1,"perevName":"Денисівка","remark":"0106 карта№32","online":true},{"id":"trans-gps:92","latitude":48.28279166666667,"longitude":25.97922,"direction":0,"speed":0,"datetime":"2018-12-23 22:40:55","routeId":14,"imei":"355227044854776","name":"A18","stateCode":"used","stateName":"used","routeName":"9A","routeColour":"magenta","inDepo":false,"busNumber":"6408","perevId":7,"perevName":"Віталій / Олег Бойко ","remark":"6408 карта №38","online":true},{"id":"trans-gps:93","latitude":48.324798333333334,"longitude":25.933795,"direction":0,"speed":0,"datetime":"2018-12-23 12:43:50","routeId":5,"imei":"355227044852341","name":"A19","stateCode":"used","stateName":"used","routeName":"13","routeColour":"brown","inDepo":true,"busNumber":"1195","perevId":1,"perevName":"Денисівка","remark":"1195 карта№21","online":true},{"id":"trans-gps:94","latitude":48.32393166666667,"longitude":25.93386,"direction":0,"speed":0,"datetime":"2018-12-23 20:40:23","routeId":6,"imei":"355227044854685","name":"A20","stateCode":"used","stateName":"used","routeName":"4","routeColour":"magenta","inDepo":true,"busNumber":"0514","perevId":1,"perevName":"Денисівка","remark":"0514 карта№11","online":true},{"id":"trans-gps:96","latitude":48.324175,"longitude":25.933716666666665,"direction":0,"speed":0,"datetime":"2018-12-23 22:38:13","routeId":5,"imei":"355227044854750","name":"A22","stateCode":"used","stateName":"used","routeName":"13","routeColour":"brown","inDepo":true,"busNumber":"1143","perevId":1,"perevName":"Денисівка","remark":"1143 карта№13","online":true},{"id":"trans-gps:106","latitude":48.27377833333333,"longitude":25.937406666666668,"direction":300,"speed":17,"datetime":"2018-12-23 22:41:35","routeId":4,"imei":"0352887077507865","name":"Acm33","stateCode":"used","stateName":"used","routeName":"5","routeColour":"orange","inDepo":false,"busNumber":"0984","perevId":1,"perevName":"Денисівка","remark":"0984 карта№22","online":true},{"id":"trans-gps:109","latitude":48.259034444444445,"longitude":25.950027777777777,"direction":0,"speed":0,"datetime":"2018-12-23 22:41:39","routeId":4,"imei":"0352887077599136","name":"Acm36","stateCode":"used","stateName":"used","routeName":"5","routeColour":"orange","inDepo":false,"busNumber":"0987","perevId":1,"perevName":"Денисівка","remark":"0987 карта№25","online":true},{"id":"trans-gps:110","latitude":48.287038333333335,"longitude":25.934028333333334,"direction":10,"speed":17,"datetime":"2018-12-23 22:41:38","routeId":6,"imei":"0352887077507949","name":"Acm37","stateCode":"used","stateName":"used","routeName":"4","routeColour":"magenta","inDepo":false,"busNumber":"1116","perevId":1,"perevName":"Денисівка","remark":"1116 карта№23","online":true},{"id":"trans-gps:114","latitude":48.27265777777778,"longitude":25.993458333333333,"direction":304,"speed":23,"datetime":"2018-12-23 22:40:36","routeId":11,"imei":"0352887077331100","name":"Ac41","stateCode":"used","stateName":"used","routeName":"9","routeColour":"magenta","inDepo":false,"busNumber":"0897","perevId":1,"perevName":"Денисівка","remark":"0897","online":true},{"id":"trans-gps:129","latitude":48.32478833333333,"longitude":25.934348333333332,"direction":0,"speed":0,"datetime":"2018-12-23 20:20:26","routeId":4,"imei":"355227045538972","name":"A52","stateCode":"used","stateName":"used","routeName":"5","routeColour":"orange","inDepo":true,"busNumber":"0902","perevId":1,"perevName":"Денисівка","remark":"0902 карта №61","online":true},{"id":"trans-gps:130","latitude":48.32443833333333,"longitude":25.934461666666667,"direction":0,"speed":0,"datetime":"2018-12-23 22:40:20","routeId":20,"imei":"355227045539392","name":"A28","stateCode":"used","stateName":"used","routeName":"A","routeColour":"navy","inDepo":false,"busNumber":"6159","perevId":1,"perevName":"Денисівка","remark":"6159","online":true},{"id":"trans-gps:131","latitude":48.282808333333335,"longitude":25.979321666666667,"direction":0,"speed":0,"datetime":"2018-12-23 22:39:34","routeId":12,"imei":"355227045540671","name":"A54","stateCode":"used","stateName":"used","routeName":"20","routeColour":"maroon","inDepo":false,"busNumber":"0553","perevId":7,"perevName":"Віталій / Олег Бойко ","remark":"0553","online":true},{"id":"trans-gps:134","latitude":48.27044,"longitude":25.983518333333333,"direction":0,"speed":0.4,"datetime":"2018-12-23 22:41:31","routeId":13,"imei":"355227045541257","name":"A57","stateCode":"used","stateName":"used","routeName":"29","routeColour":"black","inDepo":false,"busNumber":"1392","perevId":7,"perevName":"Віталій / Олег Бойко ","remark":"1392","online":true},{"id":"trans-gps:137","latitude":48.27030666666667,"longitude":25.983478333333334,"direction":0,"speed":0,"datetime":"2018-12-23 22:38:07","routeId":14,"imei":"355227045513553","name":"A60","stateCode":"used","stateName":"used","routeName":"9A","routeColour":"magenta","inDepo":false,"busNumber":"3459","perevId":7,"perevName":"Віталій / Олег Бойко ","remark":"3459 карта №89","online":true},{"id":"trans-gps:140","latitude":48.32445,"longitude":25.9336,"direction":0,"speed":0,"datetime":"2018-12-23 11:40:49","routeId":2,"imei":"355227045541273","name":"Am63","stateCode":"used","stateName":"used","routeName":"11","routeColour":"green","inDepo":true,"busNumber":"0091","perevId":2,"perevName":"Тарас","remark":"0091 карта №92","online":true},{"id":"trans-gps:142","latitude":48.324455,"longitude":25.93388,"direction":0,"speed":0,"datetime":"2018-12-23 12:00:30","routeId":2,"imei":"355227045541356","name":"Am65","stateCode":"used","stateName":"used","routeName":"11","routeColour":"green","inDepo":true,"busNumber":"1026","perevId":2,"perevName":"Тарас","remark":"1026 карта №94","online":true},{"id":"trans-gps:145","latitude":48.25559833333333,"longitude":25.967066666666668,"direction":0,"speed":0,"datetime":"2018-12-23 22:40:03","routeId":14,"imei":"355227045539582","name":"A68","stateCode":"used","stateName":"used","routeName":"9A","routeColour":"magenta","inDepo":false,"busNumber":"6001","perevId":7,"perevName":"Віталій / Олег Бойко ","remark":"6001 карта №103","online":true},{"id":"trans-gps:147","latitude":48.32461833333333,"longitude":25.933745000000002,"direction":0,"speed":0,"datetime":"2018-12-23 17:21:06","routeId":2,"imei":"355227045541463","name":"A70","stateCode":"used","stateName":"used","routeName":"11","routeColour":"green","inDepo":true,"busNumber":"0401","perevId":2,"perevName":"Тарас","remark":"0401 карта №58","online":true},{"id":"trans-gps:152","latitude":48.32387833333333,"longitude":25.934128333333334,"direction":0,"speed":0,"datetime":"2018-12-23 22:40:53","routeId":20,"imei":"355227045129301","name":"A75","stateCode":"used","stateName":"used","routeName":"A","routeColour":"navy","inDepo":true,"busNumber":"1046","perevId":1,"perevName":"Денисівка","remark":"1046 карта №96","online":true},{"id":"trans-gps:153","latitude":48.26706,"longitude":25.939368333333334,"direction":88.71,"speed":13.8,"datetime":"2018-12-23 22:41:41","routeId":11,"imei":"355227045539160","name":"A76","stateCode":"used","stateName":"used","routeName":"9","routeColour":"magenta","inDepo":false,"busNumber":"1042","perevId":1,"perevName":"Денисівка","remark":"1042 карта №97","online":true},{"id":"trans-gps:154","latitude":48.32423,"longitude":25.933593333333334,"direction":0,"speed":0,"datetime":"2018-12-23 20:26:17","routeId":5,"imei":"355227045540234","name":"A77","stateCode":"used","stateName":"used","routeName":"13","routeColour":"brown","inDepo":true,"busNumber":"0422","perevId":1,"perevName":"Денисівка","remark":"0422 карта №55","online":true},{"id":"trans-gps:155","latitude":48.32457333333333,"longitude":25.93414,"direction":0,"speed":0,"datetime":"2018-12-23 20:13:20","routeId":10,"imei":"355227045541414","name":"A78","stateCode":"used","stateName":"used","routeName":"34","routeColour":"navy","inDepo":true,"busNumber":"0047","perevId":1,"perevName":"Денисівка","remark":"0047 карта №24","online":true},{"id":"trans-gps:157","latitude":48.32452833333333,"longitude":25.934148333333333,"direction":0,"speed":0,"datetime":"2018-12-23 22:37:47","routeId":10,"imei":"355227045539640","name":"Am80","stateCode":"used","stateName":"used","routeName":"34","routeColour":"navy","inDepo":true,"busNumber":"0050","perevId":1,"perevName":"Денисівка","remark":"0050 карта №114","online":true},{"id":"trans-gps:158","latitude":48.32465,"longitude":25.934365,"direction":0,"speed":0,"datetime":"2018-12-23 22:37:23","routeId":4,"imei":"355227045526902","name":"Am85","stateCode":"used","stateName":"used","routeName":"5","routeColour":"orange","inDepo":true,"busNumber":"1173","perevId":1,"perevName":"Денисівка","remark":"1173 карта №109","online":true},{"id":"trans-gps:164","latitude":48.29264166666667,"longitude":25.932958333333332,"direction":0,"speed":0.4,"datetime":"2018-12-23 22:41:43","routeId":2,"imei":"355227045541133","name":"Am81","stateCode":"used","stateName":"used","routeName":"11","routeColour":"green","inDepo":false,"busNumber":"0082","perevId":2,"perevName":"Тарас","remark":"0082 карта №113","online":true},{"id":"trans-gps:165","latitude":48.27674,"longitude":25.930245,"direction":13.5,"speed":37.6,"datetime":"2018-12-23 22:41:38","routeId":4,"imei":"355227045540176","name":"Am83","stateCode":"used","stateName":"used","routeName":"5","routeColour":"orange","inDepo":false,"busNumber":"0903","perevId":1,"perevName":"Денисівка","remark":"0903 карта №111","online":true},{"id":"trans-gps:167","latitude":48.29304166666667,"longitude":25.93269,"direction":0,"speed":0.2,"datetime":"2018-12-23 22:41:26","routeId":3,"imei":"355227045539491","name":"Am86","stateCode":"used","stateName":"used","routeName":"12","routeColour":"blue","inDepo":false,"busNumber":"1027","perevId":2,"perevName":"Тарас","remark":"1027 карта №108","online":true},{"id":"trans-gps:168","latitude":48.324598333333334,"longitude":25.93373,"direction":0,"speed":0,"datetime":"2018-12-23 19:15:34","routeId":3,"imei":"355227045539731","name":"Am87","stateCode":"used","stateName":"used","routeName":"12","routeColour":"blue","inDepo":true,"busNumber":"1023","perevId":2,"perevName":"Тарас","remark":"1023 карта №107","online":true},{"id":"trans-gps:172","latitude":48.254545,"longitude":25.958491666666667,"direction":333.03,"speed":38.6,"datetime":"2018-12-23 22:41:38","routeId":3,"imei":"355227045540192","name":"A91","stateCode":"used","stateName":"used","routeName":"12","routeColour":"blue","inDepo":false,"busNumber":"1076","perevId":2,"perevName":"Тарас","remark":"1076 карта№71","online":true},{"id":"trans-gps:175","latitude":48.256188333333334,"longitude":25.967526666666668,"direction":0,"speed":8.3,"datetime":"2018-12-23 22:38:54","routeId":21,"imei":"355227045540317","name":"A94","stateCode":"used","stateName":"used","routeName":"38","routeColour":"deeppink","inDepo":false,"busNumber":"6823","perevId":5,"perevName":"Oleg 38 Олег Огородник","remark":"6823 карта№66","online":true},{"id":"trans-gps:176","latitude":48.270475,"longitude":25.983868333333334,"direction":0,"speed":0,"datetime":"2018-12-23 22:41:40","routeId":13,"imei":"355227045541232","name":"A95","stateCode":"used","stateName":"used","routeName":"29","routeColour":"black","inDepo":false,"busNumber":"5327","perevId":7,"perevName":"Віталій / Олег Бойко ","remark":"5327 карта№118","online":true},{"id":"trans-gps:180","latitude":48.32485833333333,"longitude":25.934223333333332,"direction":0,"speed":0,"datetime":"2018-12-23 21:59:52","routeId":4,"imei":"355227045540127","name":"A99","stateCode":"used","stateName":"used","routeName":"5","routeColour":"orange","inDepo":false,"busNumber":"0777","perevId":1,"perevName":"Денисівка","remark":"0777 карта№122","online":true},{"id":"trans-gps:182","latitude":48.26143833333333,"longitude":25.954531666666668,"direction":0,"speed":0.1,"datetime":"2018-12-23 15:07:05","routeId":12,"imei":"355227045541208","name":"A101","stateCode":"used","stateName":"used","routeName":"20","routeColour":"maroon","inDepo":false,"busNumber":"2684","perevId":7,"perevName":"Віталій / Олег Бойко ","remark":"2684 карта№124","online":true},{"id":"trans-gps:184","latitude":48.265766666666664,"longitude":25.962613333333334,"direction":118.92,"speed":30.3,"datetime":"2018-12-23 22:41:40","routeId":13,"imei":"355227045601770","name":"A102","stateCode":"used","stateName":"used","routeName":"29","routeColour":"black","inDepo":false,"busNumber":"7560","perevId":7,"perevName":"Віталій / Олег Бойко ","remark":"7560","online":true},{"id":"trans-gps:188","latitude":48.27043333333334,"longitude":25.98513833333333,"direction":126.95,"speed":24.1,"datetime":"2018-12-23 22:41:44","routeId":14,"imei":"355227045594918","name":"А106","stateCode":"used","stateName":"used","routeName":"9A","routeColour":"magenta","inDepo":false,"busNumber":"4961","perevId":7,"perevName":"Віталій / Олег Бойко ","remark":"4961","online":true},{"id":"trans-gps:190","latitude":48.324866666666665,"longitude":25.934283333333333,"direction":0,"speed":0,"datetime":"2018-12-23 20:26:52","routeId":4,"imei":"355227045594892","name":"А108","stateCode":"used","stateName":"used","routeName":"5","routeColour":"orange","inDepo":false,"busNumber":"1025","perevId":1,"perevName":"Денисівка","remark":"1025","online":true},{"id":"trans-gps:191","latitude":48.323991666666664,"longitude":25.933783333333334,"direction":0,"speed":0,"datetime":"2018-12-23 20:34:18","routeId":5,"imei":"355227045598489","name":"А109","stateCode":"used","stateName":"used","routeName":"13","routeColour":"brown","inDepo":true,"busNumber":"0299","perevId":1,"perevName":"Денисівка","remark":"0299","online":true},{"id":"trans-gps:193","latitude":48.324693333333336,"longitude":25.934045,"direction":0,"speed":0,"datetime":"2018-12-23 22:39:38","routeId":7,"imei":"355227045598786","name":"А111","stateCode":"used","stateName":"used","routeName":"6","routeColour":"sienna","inDepo":true,"busNumber":"0906","perevId":1,"perevName":"Денисівка","remark":"0906","online":true},{"id":"trans-gps:196","latitude":48.32512,"longitude":25.923133333333332,"direction":20.07,"speed":20.6,"datetime":"2018-12-23 22:41:41","routeId":6,"imei":"355227045600814","name":"A114","stateCode":"used","stateName":"used","routeName":"4","routeColour":"magenta","inDepo":false,"busNumber":"0003","perevId":1,"perevName":"Денисівка","remark":"0003 карта №3","online":true},{"id":"trans-gps:197","latitude":48.32459333333333,"longitude":25.933766666666667,"direction":0,"speed":0,"datetime":"2018-12-23 15:37:34","routeId":20,"imei":"355227045600277","name":"A115","stateCode":"used","stateName":"used","routeName":"A","routeColour":"navy","inDepo":true,"busNumber":"0745","perevId":1,"perevName":"Денисівка","remark":"0745","online":true},{"id":"transport-cv:3743","latitude":48.3883299,"longitude":25.9461482,"angle":332,"speed":138,"datetime":"2018-12-23T19:03:09","routeId":706,"difference":null,"duration":"0:3:38:35","number":"0549","startStatusDate":"2018-12-23T19:01:04","statusName":"noresponse","tteId":41},{"id":"transport-cv:7385","latitude":48.266405,"longitude":25.989435,"angle":286.64,"speed":0,"datetime":"2018-12-23T22:37:10","routeId":1501,"difference":null,"duration":"0:1:4:59","number":"0857","startStatusDate":"2018-12-23T21:32:11","statusName":"stay","tteId":41},{"id":"transport-cv:8549","latitude":48.30575,"longitude":25.9030833,"angle":0,"speed":5,"datetime":"2018-12-23T14:16:45","routeId":1924,"difference":null,"duration":"0:8:24:59","number":"2222","startStatusDate":"2018-12-23T14:16:08","statusName":"noresponse","tteId":41},{"id":"transport-cv:1141","latitude":48.32236,"longitude":25.95568,"angle":254,"speed":26,"datetime":"2018-12-23T22:41:40","routeId":null,"difference":null,"duration":"0:0:0:0","number":"305","startStatusDate":"2018-12-23T22:41:40","statusName":"move","tteId":141},{"id":"transport-cv:8405","latitude":48.2645333,"longitude":25.9883833,"angle":0,"speed":0,"datetime":"2018-12-23T22:41:12","routeId":null,"difference":null,"duration":"0:0:5:6","number":"208","startStatusDate":"2018-12-23T22:36:06","statusName":"stay","tteId":141},{"id":"transport-cv:2009","latitude":48.25125,"longitude":25.95081,"angle":282,"speed":0,"datetime":"2018-12-23T18:36:14","routeId":261,"difference":null,"duration":"0:4:5:30","number":"379","startStatusDate":"2018-12-23T18:33:42","statusName":"noresponse","tteId":141},{"id":"transport-cv:6485","latitude":48.3470549,"longitude":25.9397699,"angle":122,"speed":0,"datetime":"2018-12-23T18:43:40","routeId":706,"difference":null,"duration":"0:3:58:4","number":"0515","startStatusDate":"2018-12-23T18:32:09","statusName":"noresponse","tteId":41},{"id":"transport-cv:7145","latitude":48.2748199,"longitude":25.9245099,"angle":134,"speed":0,"datetime":"2018-12-23T17:23:29","routeId":825,"difference":null,"duration":"0:5:18:15","number":"1079","startStatusDate":"2018-12-23T16:55:26","statusName":"noresponse","tteId":41},{"id":"transport-cv:9045","latitude":48.2663333,"longitude":25.9897333,"angle":0,"speed":3,"datetime":"2018-12-23T15:22:32","routeId":1501,"difference":null,"duration":"0:7:19:12","number":"03590","startStatusDate":"2018-12-23T14:38:26","statusName":"noresponse","tteId":41},{"id":"transport-cv:2142","latitude":48.26631,"longitude":25.98875,"angle":280,"speed":0,"datetime":"2018-12-23T22:41:38","routeId":null,"difference":null,"duration":"0:0:9:27","number":"354","startStatusDate":"2018-12-23T22:32:11","statusName":"stay","tteId":141},{"id":"transport-cv:8984","latitude":48.2704499,"longitude":25.9846,"angle":45,"speed":0,"datetime":"2018-12-23T22:40:05","routeId":863,"difference":null,"duration":"0:0:32:56","number":"3456","startStatusDate":"2018-12-23T22:07:09","statusName":"stay","tteId":41},{"id":"transport-cv:6645","latitude":48.2664216667,"longitude":25.9894066667,"angle":142.39,"speed":3,"datetime":"2018-12-23T22:11:07","routeId":1501,"difference":null,"duration":"0:0:30:37","number":"0858","startStatusDate":"2018-12-23T21:56:19","statusName":"noresponse","tteId":41},{"id":"transport-cv:6544","latitude":48.2678566667,"longitude":25.9896866667,"angle":146.84,"speed":0,"datetime":"2018-12-23T22:41:04","routeId":1501,"difference":null,"duration":"0:0:0:4","number":"0358","startStatusDate":"2018-12-23T22:41:00","statusName":"stay","tteId":41},{"id":"transport-cv:2005","latitude":48.26535,"longitude":25.99103,"angle":35,"speed":6,"datetime":"2018-12-23T22:41:37","routeId":null,"difference":null,"duration":"0:0:2:0","number":"277","startStatusDate":"2018-12-23T22:39:37","statusName":"move","tteId":141},{"id":"transport-cv:6224","latitude":48.2774798,"longitude":25.9227832,"angle":344,"speed":0,"datetime":"2018-12-23T19:07:50","routeId":121,"difference":null,"duration":"0:3:33:54","number":"0399","startStatusDate":"2018-12-23T18:09:20","statusName":"noresponse","tteId":41},{"id":"transport-cv:2726","latitude":48.3264,"longitude":25.93023,"angle":216,"speed":0,"datetime":"2018-12-23T21:40:48","routeId":361,"difference":null,"duration":"0:1:0:56","number":"1050","startStatusDate":"2018-12-23T21:25:11","statusName":"noresponse","tteId":41},{"id":"transport-cv:3363","latitude":48.2751,"longitude":25.92628,"angle":159,"speed":0,"datetime":"2018-12-23T19:42:36","routeId":825,"difference":null,"duration":"0:2:59:8","number":"0725","startStatusDate":"2018-12-23T18:42:13","statusName":"noresponse","tteId":41},{"id":"transport-cv:6546","latitude":48.26634,"longitude":25.9895833333,"angle":173.69,"speed":11,"datetime":"2018-12-23T14:37:21","routeId":1501,"difference":null,"duration":"0:8:4:23","number":"0359","startStatusDate":"2018-12-23T14:37:21","statusName":"noresponse","tteId":41},{"id":"transport-cv:6545","latitude":48.28335,"longitude":25.9033,"angle":45,"speed":0,"datetime":"2018-12-23T22:39:33","routeId":1501,"difference":null,"duration":"0:0:57:54","number":"0937","startStatusDate":"2018-12-23T21:41:39","statusName":"stay","tteId":41},{"id":"transport-cv:7286","latitude":48.2705183333,"longitude":25.92781,"angle":23.02,"speed":23,"datetime":"2018-12-23T22:37:10","routeId":1501,"difference":null,"duration":"0:0:1:34","number":"0357","startStatusDate":"2018-12-23T22:35:36","statusName":"move","tteId":41},{"id":"transport-cv:1481","latitude":48.32653,"longitude":25.93055,"angle":87,"speed":2,"datetime":"2018-12-23T22:41:28","routeId":361,"difference":null,"duration":"0:0:0:16","number":"1031","startStatusDate":"2018-12-23T22:41:12","statusName":"move","tteId":41},{"id":"transport-cv:3343","latitude":48.3176,"longitude":25.9307833,"angle":90,"speed":7,"datetime":"2018-12-23T11:13:35","routeId":823,"difference":null,"duration":"0:11:28:9","number":"0272","startStatusDate":"2018-12-23T11:12:47","statusName":"noresponse","tteId":41},{"id":"transport-cv:5629","latitude":48.2695849,"longitude":25.9911165,"angle":140,"speed":0,"datetime":"2018-12-23T17:05:34","routeId":842,"difference":null,"duration":"0:5:36:10","number":"1103","startStatusDate":"2018-12-23T16:44:24","statusName":"noresponse","tteId":41},{"id":"transport-cv:5627","latitude":48.2678565,"longitude":25.9896432,"angle":172,"speed":0,"datetime":"2018-12-23T22:37:15","routeId":1922,"difference":null,"duration":"0:0:13:3","number":"1105","startStatusDate":"2018-12-23T22:24:12","statusName":"stay","tteId":41},{"id":"transport-cv:5746","latitude":48.26366,"longitude":25.95211,"angle":188,"speed":6,"datetime":"2018-12-23T22:41:28","routeId":null,"difference":null,"duration":"0:0:1:31","number":"306","startStatusDate":"2018-12-23T22:39:57","statusName":"move","tteId":141},{"id":"transport-cv:5727","latitude":48.28511,"longitude":25.9333,"angle":13,"speed":17,"datetime":"2018-12-23T22:41:39","routeId":null,"difference":null,"duration":"0:0:6:3","number":"297","startStatusDate":"2018-12-23T22:35:36","statusName":"move","tteId":141},{"id":"transport-cv:8747","latitude":48.3160183,"longitude":25.92341,"angle":75,"speed":0,"datetime":"2018-12-23T22:41:18","routeId":2042,"difference":null,"duration":"0:0:21:48","number":"383","startStatusDate":"2018-12-23T22:19:30","statusName":"move","tteId":141},{"id":"transport-cv:8724","latitude":48.2773166,"longitude":25.9226833,"angle":45,"speed":0,"datetime":"2018-12-23T21:25:28","routeId":121,"difference":null,"duration":"0:1:16:16","number":"0120","startStatusDate":"2018-12-23T21:24:22","statusName":"noresponse","tteId":41},{"id":"transport-cv:3284","latitude":48.28551,"longitude":25.9335,"angle":16,"speed":17,"datetime":"2018-12-23T22:41:35","routeId":null,"difference":null,"duration":"0:0:1:12","number":"316","startStatusDate":"2018-12-23T22:40:23","statusName":"move","tteId":141},{"id":"transport-cv:1542","latitude":48.29231,"longitude":25.93635,"angle":289,"speed":15,"datetime":"2018-12-23T22:41:34","routeId":402,"difference":null,"duration":"0:0:0:45","number":"2013","startStatusDate":"2018-12-23T22:40:49","statusName":"move","tteId":141},{"id":"transport-cv:1601","latitude":48.31541,"longitude":25.9139,"angle":283,"speed":24,"datetime":"2018-12-23T22:41:32","routeId":361,"difference":null,"duration":"0:0:7:27","number":"1099","startStatusDate":"2018-12-23T22:34:05","statusName":"move","tteId":41},{"id":"transport-cv:8528","latitude":48.3147499,"longitude":25.6993833,"angle":315,"speed":0,"datetime":"2018-12-23T22:40:00","routeId":1921,"difference":null,"duration":"0:1:43:55","number":"2309","startStatusDate":"2018-12-23T20:56:05","statusName":"stay","tteId":41},{"id":"transport-cv:5924","latitude":48.2695333,"longitude":25.9908833,"angle":270,"speed":0,"datetime":"2018-12-23T22:38:54","routeId":1922,"difference":null,"duration":"0:0:52:19","number":"1104","startStatusDate":"2018-12-23T21:46:35","statusName":"stay","tteId":41},{"id":"transport-cv:5765","latitude":48.2658666,"longitude":25.9886333,"angle":0,"speed":0,"datetime":"2018-12-23T22:40:25","routeId":null,"difference":null,"duration":"0:4:48:58","number":"302","startStatusDate":"2018-12-23T17:51:27","statusName":"move","tteId":141},{"id":"transport-cv:8553","latitude":48.26506,"longitude":25.99013,"angle":10,"speed":0,"datetime":"2018-12-23T18:59:07","routeId":401,"difference":null,"duration":"0:3:42:37","number":"373","startStatusDate":"2018-12-23T18:24:32","statusName":"noresponse","tteId":141},{"id":"transport-cv:7124","latitude":48.2751132,"longitude":25.9261615,"angle":54,"speed":0,"datetime":"2018-12-23T18:45:49","routeId":825,"difference":null,"duration":"0:3:55:55","number":"1078","startStatusDate":"2018-12-23T17:10:59","statusName":"noresponse","tteId":41},{"id":"transport-cv:8285","latitude":48.2695833,"longitude":25.9912833,"angle":45,"speed":0,"datetime":"2018-12-23T16:37:10","routeId":842,"difference":null,"duration":"0:6:4:34","number":"1069","startStatusDate":"2018-12-23T16:37:10","statusName":"noresponse","tteId":41},{"id":"transport-cv:2305","latitude":48.28893,"longitude":25.9535,"angle":101,"speed":11,"datetime":"2018-12-23T22:41:39","routeId":null,"difference":null,"duration":"0:0:0:15","number":"270","startStatusDate":"2018-12-23T22:41:24","statusName":"move","tteId":141}]}
